fastindex/__init__.py
fastindex/fastindex.py
fastindex/main.py
fastindex-0.0.4.dist-info/LICENSE
fastindex-0.0.4.dist-info/METADATA
fastindex-0.0.4.dist-info/WHEEL
fastindex-0.0.4.dist-info/top_level.txt
fastindex-0.0.4.dist-info/RECORD
