Metadata-Version: 2.1
Name: fastindex
Version: 0.0.4
Summary: fast pandas selction and indexing
Home-page: https://github.com/yonatanMedan/fastIndex
Author: Yonatan Medan
Author-email: yonatan.medan@gmail.com
License: UNKNOWN
Platform: UNKNOWN
Classifier: Programming Language :: Python :: 3
Classifier: License :: OSI Approved :: MIT License
Classifier: Operating System :: OS Independent
Requires-Dist: pandas
